[
  {
    "__EMPTY": "WARDS",
    "__EMPTY_1": "POLLING UNIT (PU)",
    "__EMPTY_2": "PVCs Collected",
    "__EMPTY_3": "NEW PVCs COLLECTED",
    "__EMPTY_4": "TOTAL PVCs COLLECTED",
    "__EMPTY_5": "15% Inc. in PVC ",
    "__EMPTY_6": "45% Target of PVC",
    "__EMPTY_7": "20K UNIT AGENTS",
    "__EMPTY_8": "5K PER VOTER",
    "__EMPTY_9": "20K INEC ADHOC",
    "__EMPTY_10": "10K UNIT SECURITY",
    "__EMPTY_11": "RAC SECURITY",
    "__EMPTY_12": "WARD AGENT 30K",
    "__EMPTY_13": "20K NYSC CORPERS",
    "__EMPTY_14": "TOTAL WARD"
  },
  {
    "IKOLE": "01",
    "__EMPTY": "IKOLE WEST I",
    "__EMPTY_1": 12,
    "__EMPTY_2": 3392,
    "__EMPTY_3": 695,
    "__EMPTY_4": 4087,
    "__EMPTY_5": 4700.05,
    "__EMPTY_6": 2115.0225,
    "__EMPTY_7": 240000,
    "__EMPTY_8": 10575112.5,
    "__EMPTY_9": 240000,
    "__EMPTY_10": 120000,
    "__EMPTY_11": 10000,
    "__EMPTY_12": 30000,
    "__EMPTY_13": 240000,
    "__EMPTY_14": 11455112.5
  },
  {
    "IKOLE": "02",
    "__EMPTY": "IKOLE WEST II",
    "__EMPTY_1": 13,
    "__EMPTY_2": 2841,
    "__EMPTY_3": 756,
    "__EMPTY_4": 3597,
    "__EMPTY_5": 4136.55,
    "__EMPTY_6": 1861.4475000000002,
    "__EMPTY_7": 260000,
    "__EMPTY_8": 9307237.500000002,
    "__EMPTY_9": 260000,
    "__EMPTY_10": 130000,
    "__EMPTY_11": 10000,
    "__EMPTY_12": 30000,
    "__EMPTY_13": 260000,
    "__EMPTY_14": 10257237.500000002
  },
  {
    "IKOLE": "03",
    "__EMPTY": "IKOLE EAST",
    "__EMPTY_1": 14,
    "__EMPTY_2": 3112,
    "__EMPTY_3": 1229,
    "__EMPTY_4": 4341,
    "__EMPTY_5": 4992.15,
    "__EMPTY_6": 2246.4674999999997,
    "__EMPTY_7": 280000,
    "__EMPTY_8": 11232337.499999998,
    "__EMPTY_9": 280000,
    "__EMPTY_10": 140000,
    "__EMPTY_11": 10000,
    "__EMPTY_12": 30000,
    "__EMPTY_13": 280000,
    "__EMPTY_14": 12252337.499999998
  },
  {
    "IKOLE": "04",
    "__EMPTY": "IKOLE NORTH",
    "__EMPTY_1": 26,
    "__EMPTY_2": 5078,
    "__EMPTY_3": 759,
    "__EMPTY_4": 5837,
    "__EMPTY_5": 6712.55,
    "__EMPTY_6": 3020.6475,
    "__EMPTY_7": 520000,
    "__EMPTY_8": 15103237.5,
    "__EMPTY_9": 520000,
    "__EMPTY_10": 260000,
    "__EMPTY_11": 10000,
    "__EMPTY_12": 30000,
    "__EMPTY_13": 520000,
    "__EMPTY_14": 16963237.5
  },
  {
    "IKOLE": "05",
    "__EMPTY": "IKOLE SOUTH",
    "__EMPTY_1": 16,
    "__EMPTY_2": 3792,
    "__EMPTY_3": 928,
    "__EMPTY_4": 4720,
    "__EMPTY_5": 5428,
    "__EMPTY_6": 2442.6,
    "__EMPTY_7": 320000,
    "__EMPTY_8": 12213000,
    "__EMPTY_9": 320000,
    "__EMPTY_10": 160000,
    "__EMPTY_11": 10000,
    "__EMPTY_12": 30000,
    "__EMPTY_13": 320000,
    "__EMPTY_14": 13373000
  },
  {
    "IKOLE": "06",
    "__EMPTY": "ARAROMI / BOLORUNDURO",
    "__EMPTY_1": 15,
    "__EMPTY_2": 2398,
    "__EMPTY_3": 796,
    "__EMPTY_4": 3194,
    "__EMPTY_5": 3673.1,
    "__EMPTY_6": 1652.895,
    "__EMPTY_7": 300000,
    "__EMPTY_8": 8264475,
    "__EMPTY_9": 300000,
    "__EMPTY_10": 150000,
    "__EMPTY_11": 10000,
    "__EMPTY_12": 30000,
    "__EMPTY_13": 300000,
    "__EMPTY_14": 9354475
  },
  {
    "IKOLE": "07",
    "__EMPTY": "IJESA ISU",
    "__EMPTY_1": 21,
    "__EMPTY_2": 3808,
    "__EMPTY_3": 622,
    "__EMPTY_4": 4430,
    "__EMPTY_5": 5094.5,
    "__EMPTY_6": 2292.525,
    "__EMPTY_7": 420000,
    "__EMPTY_8": 11462625,
    "__EMPTY_9": 420000,
    "__EMPTY_10": 210000,
    "__EMPTY_11": 10000,
    "__EMPTY_12": 30000,
    "__EMPTY_13": 420000,
    "__EMPTY_14": 12972625
  },
  {
    "IKOLE": "08",
    "__EMPTY": "ODO AYEDUN I",
    "__EMPTY_1": 18,
    "__EMPTY_2": 2405,
    "__EMPTY_3": 618,
    "__EMPTY_4": 3023,
    "__EMPTY_5": 3476.45,
    "__EMPTY_6": 1564.4025,
    "__EMPTY_7": 360000,
    "__EMPTY_8": 7822012.5,
    "__EMPTY_9": 360000,
    "__EMPTY_10": 180000,
    "__EMPTY_11": 10000,
    "__EMPTY_12": 30000,
    "__EMPTY_13": 360000,
    "__EMPTY_14": 9122012.5
  },
  {
    "IKOLE": "09",
    "__EMPTY": "ODO AYEDUN / AYEBODE",
    "__EMPTY_1": 12,
    "__EMPTY_2": 2061,
    "__EMPTY_3": 925,
    "__EMPTY_4": 2986,
    "__EMPTY_5": 3433.9,
    "__EMPTY_6": 1545.255,
    "__EMPTY_7": 240000,
    "__EMPTY_8": 7726275.000000001,
    "__EMPTY_9": 240000,
    "__EMPTY_10": 120000,
    "__EMPTY_11": 10000,
    "__EMPTY_12": 30000,
    "__EMPTY_13": 240000,
    "__EMPTY_14": 8606275
  },
  {
    "IKOLE": "10",
    "__EMPTY": "OKE AYEDUN",
    "__EMPTY_1": 18,
    "__EMPTY_2": 2747,
    "__EMPTY_3": 773,
    "__EMPTY_4": 3520,
    "__EMPTY_5": 4048,
    "__EMPTY_6": 1821.6000000000001,
    "__EMPTY_7": 360000,
    "__EMPTY_8": 9108000,
    "__EMPTY_9": 360000,
    "__EMPTY_10": 180000,
    "__EMPTY_11": 10000,
    "__EMPTY_12": 30000,
    "__EMPTY_13": 360000,
    "__EMPTY_14": 10408000
  },
  {
    "IKOLE": "11",
    "__EMPTY": "IPAO / OKE AKO / IRELE",
    "__EMPTY_1": 16,
    "__EMPTY_2": 3124,
    "__EMPTY_3": 1005,
    "__EMPTY_4": 4129,
    "__EMPTY_5": 4748.35,
    "__EMPTY_6": 2136.7575,
    "__EMPTY_7": 320000,
    "__EMPTY_8": 10683787.5,
    "__EMPTY_9": 320000,
    "__EMPTY_10": 160000,
    "__EMPTY_11": 10000,
    "__EMPTY_12": 30000,
    "__EMPTY_13": 320000,
    "__EMPTY_14": 11843787.5
  },
  {
    "IKOLE": "12",
    "__EMPTY": "ITAPAJI / IYEMERO",
    "__EMPTY_1": 8,
    "__EMPTY_2": 1792,
    "__EMPTY_3": 612,
    "__EMPTY_4": 2404,
    "__EMPTY_5": 2764.6,
    "__EMPTY_6": 1244.07,
    "__EMPTY_7": 160000,
    "__EMPTY_8": 6220350,
    "__EMPTY_9": 160000,
    "__EMPTY_10": 80000,
    "__EMPTY_11": 10000,
    "__EMPTY_12": 30000,
    "__EMPTY_13": 160000,
    "__EMPTY_14": 6820350
  },
  {
    "__EMPTY_1": 189,
    "__EMPTY_2": 36550,
    "__EMPTY_3": 9718,
    "__EMPTY_4": 46268,
    "__EMPTY_5": 53208.2,
    "__EMPTY_6": 23943.69,
    "__EMPTY_7": 3780000,
    "__EMPTY_8": 119718450,
    "__EMPTY_9": 3780000,
    "__EMPTY_10": 1890000,
    "__EMPTY_11": 120000,
    "__EMPTY_12": 360000,
    "__EMPTY_13": 3780000,
    "__EMPTY_14": 133428450
  },
  {
    "__EMPTY": "LG PARTY CHAIRMAN @ N100K",
    "__EMPTY_14": 100000
  },
  {
    "__EMPTY": "POLICE IN LG @N250K PER LG",
    "__EMPTY_14": 250000
  },
  {
    "__EMPTY": "DSS IN LG @N100K PER LG",
    "__EMPTY_14": 100000
  },
  {
    "__EMPTY": "NSCDC IN LG @N100K PER LG",
    "__EMPTY_14": 100000
  },
  {
    "__EMPTY": "AMOTEKUN IN LG @N100K PER LG",
    "__EMPTY_14": 100000
  },
  {
    "__EMPTY": "PEACE CORPS IN LG @N50K PER LG",
    "__EMPTY_14": 50000
  },
  {
    "__EMPTY": "TOTAL",
    "__EMPTY_14": 134128450
  }
]